wasserplan
