Metadata-Version: 1.1
Name: wasserplan
Version: 0.1.3
Summary: 1-Wasserstein distances between districting plans
Home-page: https://github.com/vrdi/geometry-of-graph-partitions
Author: Parker J. Rule
Author-email: parker.rule@tufts.edu
License: UNKNOWN
Platform: UNKNOWN
Classifier: Programming Language :: Python :: 3.6
Classifier: Programming Language :: Python :: 3.7
Classifier: Operating System :: OS Independent
Classifier: License :: OSI Approved :: BSD License
